lomadeepy/__init__.py
lomadeepy/lomadee.py
lomadeepy-1.0.0.dist-info/LICENSE
lomadeepy-1.0.0.dist-info/METADATA
lomadeepy-1.0.0.dist-info/WHEEL
lomadeepy-1.0.0.dist-info/top_level.txt
lomadeepy-1.0.0.dist-info/RECORD
