Metadata-Version: 2.1
Name: lomadeepy
Version: 1.0.0
Summary: Implementação da API de ofertas do lomadee em Python. Não Oficial.
Home-page: https://github.com/gustavopinho/lomadeepy.git
Author: Gustavo Pinho
Author-email: dev@gustavopinho.com
License: MIT License
Keywords: api lomadee python ofertas
Platform: UNKNOWN
Requires-Dist: requests
